{
  "main": {
    "id": "14c2055c738a10cc",
    "type": "split",
    "children": [
      {
        "id": "872c0d99e27fb1c9",
        "type": "tabs",
        "children": [
          {
            "id": "a574822046f3b135",
            "type": "leaf",
            "state": {
              "type": "markdown",
              "state": {
                "file": "DonEx Architecture.md",
                "mode": "source",
                "source": false
              }
            }
          },
          {
            "id": "1b5d7b1d98b34d0e",
            "type": "leaf",
            "state": {
              "type": "markdown",
              "state": {
                "file": "DonEx Architecture.md",
                "mode": "source",
                "source": false
              }
            }
          },
          {
            "id": "43962d11ff7cb292",
            "type": "leaf",
            "state": {
              "type": "markdown",
              "state": {
                "file": "DonEx Architecture.md",
                "mode": "source",
                "source": false
              }
            }
          }
        ],
        "currentTab": 2
      }
    ],
    "direction": "vertical"
  },
  "left": {
    "id": "a2d6f33438956e87",
    "type": "split",
    "children": [
      {
        "id": "11ef360470ced186",
        "type": "tabs",
        "children": [
          {
            "id": "395e69c02044e275",
            "type": "leaf",
            "state": {
              "type": "file-explorer",
              "state": {
                "sortOrder": "alphabetical"
              }
            }
          },
          {
            "id": "6843202c02fc0638",
            "type": "leaf",
            "state": {
              "type": "search",
              "state": {
                "query": "",
                "matchingCase": false,
                "explainSearch": false,
                "collapseAll": false,
                "extraContext": false,
                "sortOrder": "alphabetical"
              }
            }
          },
          {
            "id": "025bcac32a8ca9b7",
            "type": "leaf",
            "state": {
              "type": "bookmarks",
              "state": {}
            }
          }
        ],
        "currentTab": 1
      }
    ],
    "direction": "horizontal",
    "width": 300
  },
  "right": {
    "id": "28431fbb866a48ec",
    "type": "split",
    "children": [
      {
        "id": "57e139199d837049",
        "type": "tabs",
        "children": [
          {
            "id": "90d3fdde80a5d4e8",
            "type": "leaf",
            "state": {
              "type": "backlink",
              "state": {
                "file": "DonEx Architecture.md",
                "collapseAll": true,
                "extraContext": false,
                "sortOrder": "alphabetical",
                "showSearch": false,
                "searchQuery": "",
                "backlinkCollapsed": false,
                "unlinkedCollapsed": true
              }
            }
          },
          {
            "id": "2e7d72dee5bacd4a",
            "type": "leaf",
            "state": {
              "type": "outgoing-link",
              "state": {
                "file": "DonEx Architecture.md",
                "linksCollapsed": false,
                "unlinkedCollapsed": true
              }
            }
          },
          {
            "id": "a3dedf6cd999f58a",
            "type": "leaf",
            "state": {
              "type": "tag",
              "state": {
                "sortOrder": "frequency",
                "useHierarchy": true
              }
            }
          },
          {
            "id": "bb0c3bbf305d28c4",
            "type": "leaf",
            "state": {
              "type": "outline",
              "state": {
                "file": "DonEx Architecture.md"
              }
            }
          }
        ],
        "currentTab": 3
      }
    ],
    "direction": "horizontal",
    "width": 300
  },
  "left-ribbon": {
    "hiddenItems": {
      "switcher:Open quick switcher": false,
      "graph:Open graph view": false,
      "canvas:Create new canvas": false,
      "daily-notes:Open today's daily note": false,
      "templates:Insert template": false,
      "command-palette:Open command palette": false
    }
  },
  "active": "43962d11ff7cb292",
  "lastOpenFiles": [
    "donex.drawio.png",
    "DonEx Architecture.md",
    "donex.drawio",
    "Ý tưởng hackathon.md"
  ]
}